README.rst
setup.py
zlgg/__init__.py
zlgg/test.py
zlgg.egg-info/PKG-INFO
zlgg.egg-info/SOURCES.txt
zlgg.egg-info/dependency_links.txt
zlgg.egg-info/requires.txt
zlgg.egg-info/top_level.txt
zlgg/analysis/__init__.py
zlgg/analysis/table.py
zlgg/clear/__init__.py
zlgg/clear/ps.py
zlgg/clear/table.py
zlgg/core/__init__.py
zlgg/core/words.py
zlgg/core/words.txt
zlgg/extdata/__init__.py
zlgg/extdata/all.py
zlgg/extdata/ps.py
zlgg/extdata/table.py
zlgg/stddata/__init__.py
zlgg/stddata/k.py
zlgg/stddata/v.py
zlgg/test/__init__.py
zlgg/test/tb_clear_qt.py
zlgg/zljianzhu/__init__.py